<?xml version="1.0" encoding="utf-8" ?>
<SampleMetadata>
	<ID>68c24f2d-128a-4e51-9290-5784417adbfd</ID>
	<IsFullApplication>true</IsFullApplication>
	<Gallery>true</Gallery>
	<Level>Intermediate</Level>
	<Tags>Android, iOS, Xamarin.UITest, Test-Cloud</Tags>
	<SupportedPlatforms>Android,iOS</SupportedPlatforms>
	<brief>This sample is the companion code for the Introduction to Xamarin.UITest and the Submitting Tests to Xamarin Test Cloud guides. It has some simple examples of tests written using Xamarin.UITest </brief>
    <LicenseRequirement>Indie</LicenseRequirement>
</SampleMetadata>
